{
    "Inactive Pipeline": {
        "Default": [
            "1.0000000000"
        ],
        "US West (Oregon)": [
            "1.0000000000"
        ],
        "US East (N. Virginia)": [
            "1.0000000000"
        ],
        "EU (Ireland)": [
            "1.0000000000"
        ],
        "Asia Pacific (Tokyo)": [
            "0.9524000000"
        ],
        "Asia Pacific (Sydney)": [
            "1.0000000000"
        ]
    },
    "Active Pipeline running on AWS High Frequency": {
        "Default": [
            "1.0000000000"
        ],
        "US West (Oregon)": [
            "1.0000000000"
        ],
        "US East (N. Virginia)": [
            "1.0000000000"
        ],
        "EU (Ireland)": [
            "1.0000000000"
        ],
        "Asia Pacific (Tokyo)": [
            "0.9524000000"
        ],
        "Asia Pacific (Sydney)": [
            "1.0000000000"
        ]
    },
    "Active Pipeline running on On-Premise Low Frequency": {
        "Default": [
            "1.5000000000"
        ],
        "US West (Oregon)": [
            "1.5000000000"
        ],
        "US East (N. Virginia)": [
            "1.5000000000"
        ],
        "EU (Ireland)": [
            "1.5000000000"
        ],
        "Asia Pacific (Tokyo)": [
            "1.4286000000"
        ],
        "Asia Pacific (Sydney)": [
            "1.5000000000"
        ]
    },
    "Active Pipeline running on AWS Low Frequency": {
        "Default": [
            "0.6000000000"
        ],
        "US West (Oregon)": [
            "0.6000000000"
        ],
        "US East (N. Virginia)": [
            "0.6000000000"
        ],
        "EU (Ireland)": [
            "0.6000000000"
        ],
        "Asia Pacific (Tokyo)": [
            "0.5715000000"
        ],
        "Asia Pacific (Sydney)": [
            "0.6000000000"
        ]
    },
    "Active Pipeline running on On-Premise High Frequency": {
        "Default": [
            "2.5000000000"
        ],
        "US West (Oregon)": [
            "2.5000000000"
        ],
        "US East (N. Virginia)": [
            "2.5000000000"
        ],
        "EU (Ireland)": [
            "2.5000000000"
        ],
        "Asia Pacific (Tokyo)": [
            "2.3810000000"
        ],
        "Asia Pacific (Sydney)": [
            "2.5000000000"
        ]
    }
}